servicemapper/__init__.py
servicemapper/decorators.py
servicemapper/ioc.py
servicemapper/logging_client.py
servicemapper/mapper_worker.py
servicemapper/service_connector.py
servicemapper/types.py
servicemapper/examples/__init__.py
servicemapper/examples/main.py
servicemapper/examples/sample_service_mapper.py
servicemapper-0.0.13.dist-info/AUTHORS.rst
servicemapper-0.0.13.dist-info/LICENSE
servicemapper-0.0.13.dist-info/METADATA
servicemapper-0.0.13.dist-info/WHEEL
servicemapper-0.0.13.dist-info/entry_points.txt
servicemapper-0.0.13.dist-info/top_level.txt
servicemapper-0.0.13.dist-info/RECORD
